Workbook

Sheet Summary
A1: Mexico Staking (MEX) — QA Master Checklist
A3: Checklist | B3: Case Count | C3: Not tested | D3: Passed | E3: Failed | F3: Blocked | G3: Skipped
A4: Smoke Fast | B4: 25 | C4: =COUNTIF('Smoke Fast'!E2:E26,"Not tested") | D4: =COUNTIF('Smoke Fast'!E2:E26,"Passed") | E4: =COUNTIF('Smoke Fast'!E2:E26,"Failed") | F4: =COUNTIF('Smoke Fast'!E2:E26,"Blocked") | G4: =COUNTIF('Smoke Fast'!E2:E26,"Skipped")
A5: Break It Tonight | B5: 28 | C5: =COUNTIF('Break It Tonight'!E2:E29,"Not tested") | D5: =COUNTIF('Break It Tonight'!E2:E29,"Passed") | E5: =COUNTIF('Break It Tonight'!E2:E29,"Failed") | F5: =COUNTIF('Break It Tonight'!E2:E29,"Blocked") | G5: =COUNTIF('Break It Tonight'!E2:E29,"Skipped")
A6: Solana Specific | B6: 24 | C6: =COUNTIF('Solana Specific'!E2:E25,"Not tested") | D6: =COUNTIF('Solana Specific'!E2:E25,"Passed") | E6: =COUNTIF('Solana Specific'!E2:E25,"Failed") | F6: =COUNTIF('Solana Specific'!E2:E25,"Blocked") | G6: =COUNTIF('Solana Specific'!E2:E25,"Skipped")
A8: Total | B8: =SUM(B4:B6) | C8: =SUM(C4:C6) | D8: =SUM(D4:D6) | E8: =SUM(E4:E6) | F8: =SUM(F4:F6) | G8: =SUM(G4:G6)
A10: Open findings not part of the original checklists (see bug_reports/):
A11: BUG-001 | B11: Helius RPC API key exposed in plain text query parameter on the front end | C11: Critical
A12: BUG-002 | B12: Verify rounding behavior on small/frequent claims (dust) | C12: Medium — pending verification

Sheet Smoke Fast
A1: # | B1: Title | C1: How to test | D1: Expected Result | E1: Status | F1: Priority
A2: 1 | B2: Connect Phantom wallet on devnet | C2: Open mexicoweb-dev.up.railway.app, click "Connect Wallet", select Phantom, approve connection | D2: Wallet connects successfully, address and SOL balance are shown in the header | E2: Not tested
A3: 2 | B3: Switch Phantom network to Devnet | C3: In Phantom settings, switch active network to Devnet, reload the app | D3: App detects Devnet and loads pool/position data without errors | E3: Not tested
A4: 3 | B4: Fund wallet with devnet SOL | C4: Use faucet.solana.com (or `solana airdrop`) to send devnet SOL to the connected wallet | D4: Wallet balance increases by the requested SOL amount within a few seconds | E4: Not tested
A5: 4 | B5: Obtain devnet MEX tokens | C5: Request a transfer from the team dev-wallet (or run the provided mint script) to the test wallet | D5: Test wallet receives the requested amount of MEX on devnet | E5: Not tested
A6: 5 | B6: Add MEX token to Phantom | C6: In Phantom token list enable the hidden-token toggle for MEX, or add manually by mint address | D6: MEX balance and logo/ticker are visible in Phantom's asset list | E6: Not tested
A7: 6 | B7: Verify pool stats on Stake page load | C7: Open the Stake page with a wallet connected | D7: Global cap, currently staked amount, pool occupancy indicator and APR range are displayed and internally consistent (occupied <= cap) | E7: Not tested
A8: 7 | B8: Create first staking position at minimum amount | C8: Enter the minimum allowed stake amount and minimum lock tier, submit the stake transaction, approve in Phantom | D8: Transaction confirms, a new position appears in "My Positions" with correct amount and lock end date | E8: Not tested
A9: 8 | B9: Verify ATA/position account creation on first stake | C9: After the first stake, inspect the transaction on a devnet explorer | D9: Instruction creates the position PDA and (if needed) the associated token account for MEX | E9: Not tested
A10: 9 | B10: Verify position details match input | C10: Open the new position card in the UI | D10: Displayed staked amount, lock duration and start date match what was submitted | E10: Not tested
A11: 10 | B11: Perform Day 1 daily check-in | C11: On the position, click "Check-in" for the first time | D11: Check-in succeeds, streak counter shows 1, and the current rate reflects the primary-tier starting value | E11: Not tested
A12: 11 | B12: Verify check-in cannot be repeated same day | C12: Click "Check-in" again immediately after a successful check-in | D12: Action is blocked (button disabled or on-chain rejection) with a clear "already checked in today" message | E12: Not tested
A13: 12 | B13: Attempt to unstake before lock period ends | C13: On a position still inside its lock window, click "Unstake" | D13: Action is blocked by the UI and/or rejected on-chain | E13: Not tested
... A26: 25 | B26: Verify indexer/API reflects final on-chain state | C26: Query the read-only API for the test wallet after the smoke run completes | D26: API response matches on-chain state (positions, balances, streaks) with no stale or missing data | E26: Not tested

Sheet Break It Tonight
A1: # | B1: Title | C1: How to test | D1: Expected Result | E1: Status | F1: Priority
A2: 1 | B2: Access admin-only UI route without being a multisig signer | C2: Navigate directly to the admin/config URL with a non-signer wallet connected | D2: Route either redirects/hides admin controls, and any admin action attempted from it is rejected on-chain (not just hidden by the front end) | E2: Not tested
A3: 2 | B3: Call read-only API for another wallet's data without authorization | C3: Using DevTools/curl, request the API endpoint with an arbitrary wallet address that is not the connected one | D3: API returns data (by design, if truly read-only/public) or is explicitly rejected — verify the response matches the intended access model, not an accidental broader leak (e.g. internal fields, other users' PII) | E3: Not tested
A4: 3 | B4: Bypass "connect wallet" gate to reach staking actions | C4: Try to open the Stake/Claim/Unstake screens directly via URL without connecting a wallet | D4: Screens either require connection before allowing any signable action, or any attempt to build/sign a transaction fails gracefully | E4: Not tested
A5: 4 | B5: Submit stake instruction referencing a different wallet as the position owner (IDOR) | C5: Copy the stake request from the Network tab, replace the "owner"/"authority" account with a victim wallet's pubkey, sign with the attacker's key and submit | D5: Program rejects the transaction (owner/authority must match signer) — stake is not created against the victim's PDA | E5: Not tested
A6: 5 | B6: Submit claim instruction for a position owned by another wallet | C6: Modify the intercepted claim transaction to target another user's known position PDA while signing as attacker | D6: Program rejects the instruction because the signer is not the authority on that position account | E6: Not tested
A7: 6 | B7: Submit unstake instruction for a position PDA belonging to another wallet | C7: Modify the intercepted unstake transaction's position account to a victim's PDA, keep attacker as signer | D7: Program rejects the instruction | E7: Not tested
A8: 7 | B8: Attempt daily check-in on a position owned by another wallet | C8: Modify the intercepted check-in transaction to reference another user's position while signing as attacker | D8: Program rejects the check-in | E8: Not tested
A9: 8 | B9: Attempt to redirect claim/unstake payout to an arbitrary destination account | C9: Edit the destination token account in the intercepted transaction to an attacker-controlled ATA that isn't derived from the position owner | D9: Program validates the destination account is the owner's associated token account (or explicit owner check) and rejects mismatched destinations | E9: Not tested
A10: 9 | B10: Race two simultaneous stakes near the global cap boundary | C10: From two wallets, submit stakes simultaneously that would jointly push total staked just over the 30,000,000 MEX global cap | D10: Only stakes that keep the total at or under the cap succeed | E10: Not tested
A11: 10 | B11: Race two simultaneous stakes near the per-wallet cap boundary | C11: From the same wallet, fire two stake transactions concurrently that would jointly exceed the 500,000 MEX per-wallet cap | D11: Only the portion within the cap succeeds | E11: Not tested
A12: 11 | B12: Race claim and compound on the same position | C12: Trigger "Claim" and "Compound" on the same position at nearly the same time (two browser tabs / two quick clicks) | D12: Only one action succeeds per reward unit | E12: Not tested
A13: 12 | B13: Race two unstake requests on the same position | C13: Submit two unstake transactions for the same position in quick succession | D13: Only the first succeeds | E13: Not tested
... A29: 28 | B29: Verify client-side validation errors have matching on-chain enforcement for every blocked action found above | C29: For each case where the UI blocks an action, also attempt the equivalent raw instruction via DevTools-copied request | D29: Every UI-side restriction has an equivalent on-chain check | E29: Not tested

Sheet Solana Specific
A1: # | B1: Title | C1: How to test | D1: Expected Result | E1: Status | F1: Priority
A2: 1 | B2: Verify rent-exempt minimum is reserved for new position account | C2: Create a new staking position and inspect the lamports balance of the created position PDA on a devnet explorer | D2: Position account holds at least the rent-exempt minimum for its data size, paid by the staker | E2: Not tested
A3: 2 | B3: Verify ATA is created once per (wallet, mint) and reused | C3: Stake twice from the same wallet and inspect whether a new associated token account is created each time | D3: The MEX ATA is created only on the first interaction and reused on subsequent stakes | E3: Not tested
A4: 3 | B4: Verify rent is refunded when a position account is closed | C4: Fully unstake a position so its account is closed, then check the wallet's SOL balance change | D4: Rent lamports from the closed position account are returned to the appropriate owner (staker or fee payer, per design) minus network fees | E4: Not tested
A5: 4 | B5: Create multiple concurrent positions and test batch claim compute budget | C5: Open 8–10+ independent positions from one wallet, then attempt to claim/compound all of them in as few transactions as the UI supports | D5: All claims complete without hitting the compute budget limit, or the UI correctly batches/paginates instructions across multiple transactions when the limit would be exceeded | E5: Not tested
A6: 5 | B6: Verify per-transaction compute budget headroom on claim-all | C6: Use a devnet explorer to inspect compute units consumed by a "claim all positions" transaction with many positions | D6: Compute units consumed stay under the network's per-transaction limit (or the app explicitly requests a higher compute budget via `ComputeBudgetProgram` and it's still within protocol limits) | E6: Not tested
A7: 6 | B7: Attempt to pass a PDA with incorrect seeds as the position account | C7: Modify the intercepted transaction to reference a manually derived (wrong-seed) PDA instead of the real position account, then submit | D7: Program's account validation (seeds/bump check) rejects the mismatched PDA | E7: Not tested
A8: 7 | B8: Attempt to pass an account from a different program as the position account | C8: Substitute the position account field with an account owned by an unrelated program (e.g. the System Program's rent sysvar or another dApp's account) | D8: Program rejects the instruction due to owner/discriminator mismatch on the substituted account | E8: Not tested
A9: 8 | B9: Attempt to substitute the pool config account with an attacker-controlled account | C9: In an admin-adjacent or stake instruction, replace the expected global pool-config account with a fake account crafted by the attacker | D9: Program validates the pool-config account against its expected address/PDA and rejects the substitution | E9: Not tested
A10: 9 | B10: Verify program derives and validates PDAs server-side, not trusting client-supplied pubkeys | C10: Review/observe on-chain behavior when supplying a syntactically valid but not-derived-from-seeds pubkey for any PDA account argument | D10: Program independently derives the expected PDA and rejects the instruction if the supplied account doesn't match | E10: Not tested
A11: 10 | B11: Verify lock-end timestamp is computed from on-chain Clock, not client time | C11: Change the local device clock forward by several days, then check the displayed and enforced lock/unlock state for an active position | D11: Lock/unlock state is unaffected by the device clock change | E11: Not tested
A12: 11 | B12: Verify check-in day boundary uses on-chain Clock | C12: Attempt a second check-in right around local midnight while the device clock is skewed relative to UTC | D12: One check-in per day is enforced based on on-chain time, not the skewed local device time | E12: Not tested
A13: 12 | B13: Verify behavior right at a day boundary (UTC midnight) for check-in | C13: Perform a check-in a few minutes before and a few minutes after a UTC day boundary | D13: Check-ins on either side of the real on-chain day boundary are treated as separate days | E13: Not tested
... A25: 24 | B25: Verify ATA/account rent accounting does not leak lamports on repeated stake/unstake cycles | C25: Perform several full stake-then-unstake cycles on the same wallet and track cumulative SOL spent beyond documented network fees | D25: No unexplained SOL/lamport loss occurs beyond rent (correctly refunded on close) and standard transaction fees | E25: Not tested
